LICENSE
README.md
setup.py
tap_skubana/__init__.py
tap_skubana/catalog.py
tap_skubana/client.py
tap_skubana/streams.py
tap_skubana.egg-info/PKG-INFO
tap_skubana.egg-info/SOURCES.txt
tap_skubana.egg-info/dependency_links.txt
tap_skubana.egg-info/entry_points.txt
tap_skubana.egg-info/requires.txt
tap_skubana.egg-info/top_level.txt
tap_skubana/schemas/application_properties.json
tap_skubana/schemas/company_info.json
tap_skubana/schemas/custom_field_definition.json
tap_skubana/schemas/incoterm_ship_rule.json
tap_skubana/schemas/inventory.json
tap_skubana/schemas/listing.json
tap_skubana/schemas/order.json
tap_skubana/schemas/payment_type.json
tap_skubana/schemas/product.json
tap_skubana/schemas/product_stock_total.json
tap_skubana/schemas/purchase_order.json
tap_skubana/schemas/purchase_order_format.json
tap_skubana/schemas/rma.json
tap_skubana/schemas/sales_channel.json
tap_skubana/schemas/shipment.json
tap_skubana/schemas/shipping_carrier.json
tap_skubana/schemas/shipping_package.json
tap_skubana/schemas/shipping_provider.json
tap_skubana/schemas/shipping_service.json
tap_skubana/schemas/stock_transfer.json
tap_skubana/schemas/vendor.json
tap_skubana/schemas/vendor_product.json
tap_skubana/schemas/warehouse.json